dummy.cpython-311-x86_64-linux-gnu.so
test/__init__.py
test/callchain_test.py
callchain_checker-0.0.3.dist-info/WHEEL
callchain_checker-0.0.3.dist-info/METADATA
callchain_checker-0.0.3.dist-info/RECORD
callchain_checker-0.0.3.dist-info/LICENSE
callchain_checker-0.0.3.dist-info/top_level.txt
callchain_checker/__init__.py
callchain_checker/ccc
callchain_checker/py.typed
callchain_checker/callchain_checker.py
