Metadata-Version: 2.1
Name: callchain-checker
Version: 0.0.3
Summary: A C/C++ code callchain checker
Home-page: https://github.com/DeadCodeProductions/callchain-checker
Author: Theodoros Theodoridis
Author-email: theodort@inf.ethz.ch
License: Apache License 2.0
Classifier: Programming Language :: Python :: 3
Requires-Python: >=3.10
License-File: LICENSE
Requires-Dist: diopter (>=0.0.9)
